[
  {
    "id": "body-step-small"
  },
  {
    "id": "body-cta",
    "index": "0"
  },
  {
    "id": "body-signature"
  },
  {
    "id": "body-cta",
    "index": "1"
  }
]

[
  {
    "id": "header-snippet"
  },
  {
    "id": "header-adhoc-illustration"
  },
  {
    "id": "body-title-text"
  },
  {
    "id": "body-cta",
    "index": "0"
  },
  {
    "id": "body-box-zero2"
  },
  {
    "id": "body-title",
    "index": "0"
  },
  {
    "id": "body-text",
    "index": "0"
  },
  {
    "id": "body-title",
    "index": "1"
  },
  {
    "id": "body-text",
    "index": "1"
  },
  {
    "id": "body-cta",
    "index": "1"
  },
  {
    "id": "body-signature"
  },
  {
    "id": "footer"
  }
]